mxcurpy/__init__.py
mxcurpy/curp.py
mxcurpy/non_convenient_words.py
mxcurpy/rfc.py
mxcurpy/states.py
mxcurpy/utils.py
mxcurpy-0.2.1.dist-info/LICENSE.txt
mxcurpy-0.2.1.dist-info/WHEEL
mxcurpy-0.2.1.dist-info/METADATA
mxcurpy-0.2.1.dist-info/RECORD
