Metadata-Version: 2.1
Name: mxcurpy
Version: 0.2.1
Summary: Compute CURP and RFC for Mexican Citizens
Home-page: https://github.com/hectorip/mxcurpy
License: MIT
Keywords: curp,mexico
Author: Héctor Iván Patricio Moreno
Author-email: hectorivanpatriciomoreno@gmail.com
Requires-Python: >=3.6,<4.0
Classifier: License :: OSI Approved :: MIT License
Classifier: Programming Language :: Python :: 3
Classifier: Programming Language :: Python :: 3.10
Classifier: Programming Language :: Python :: 3.6
Classifier: Programming Language :: Python :: 3.7
Classifier: Programming Language :: Python :: 3.8
Classifier: Programming Language :: Python :: 3.9
